[{"pc":0,"gasCost":3},{"pc":2,"gasCost":3},{"pc":4,"gasCost":12},{"pc":5,"gasCost":3},{"pc":7,"gasCost":2},{"pc":8,"gasCost":3},{"pc":9,"gasCost":3},{"pc":12,"gasCost":10},{"pc":314,"gasCost":1},{"pc":315,"gasCost":3},{"pc":318,"gasCost":3},{"pc":321,"gasCost":8},{"pc":1460,"gasCost":1},{"pc":1461,"gasCost":3},{"pc":1463,"gasCost":200},{"pc":1464,"gasCost":3},{"pc":1466,"gasCost":3},{"pc":1467,"gasCost":3},{"pc":1468,"gasCost":3},{"pc":1469,"gasCost":3},{"pc":1471,"gasCost":3},{"pc":1472,"gasCost":3},{"pc":1473,"gasCost":3},{"pc":1476,"gasCost":10},{"pc":1481,"gasCost":1},{"pc":1482,"gasCost":3},{"pc":1484,"gasCost":3},{"pc":1486,"gasCost":3},{"pc":1488,"gasCost":60},{"pc":1489,"gasCost":3},{"pc":1490,"gasCost":2},{"pc":1491,"gasCost":3},{"pc":1492,"gasCost":3},{"pc":1494,"gasCost":3},{"pc":1495,"gasCost":3},{"pc":1496,"gasCost":3},{"pc":1497,"gasCost":3},{"pc":1499,"gasCost":3},{"pc":1501,"gasCost":3},{"pc":1502,"gasCost":3},{"pc":1504,"gasCost":3},{"pc":1505,"gasCost":42},{"pc":1506,"gasCost":200},{"pc":1507,"gasCost":3},{"pc":1509,"gasCost":3},{"pc":1510,"gasCost":3},{"pc":1511,"gasCost":3},{"pc":1514,"gasCost":10},{"pc":1515,"gasCost":3},{"pc":1517,"gasCost":3},{"pc":1518,"gasCost":0}]
