[{"pc":0,"gasCost":3},{"pc":2,"gasCost":3},{"pc":4,"gasCost":12},{"pc":5,"gasCost":3},{"pc":7,"gasCost":2},{"pc":8,"gasCost":3},{"pc":9,"gasCost":3},{"pc":12,"gasCost":10},{"pc":13,"gasCost":3},{"pc":18,"gasCost":3},{"pc":20,"gasCost":3},{"pc":22,"gasCost":60},{"pc":23,"gasCost":3},{"pc":25,"gasCost":3},{"pc":26,"gasCost":5},{"pc":27,"gasCost":3},{"pc":28,"gasCost":3},{"pc":33,"gasCost":3},{"pc":34,"gasCost":3},{"pc":35,"gasCost":3},{"pc":38,"gasCost":10},{"pc":39,"gasCost":3},{"pc":40,"gasCost":3},{"pc":45,"gasCost":3},{"pc":46,"gasCost":3},{"pc":49,"gasCost":10},{"pc":50,"gasCost":3},{"pc":51,"gasCost":3},{"pc":56,"gasCost":3},{"pc":57,"gasCost":3},{"pc":60,"gasCost":10},{"pc":61,"gasCost":3},{"pc":62,"gasCost":3},{"pc":67,"gasCost":3},{"pc":68,"gasCost":3},{"pc":71,"gasCost":10},{"pc":72,"gasCost":3},{"pc":73,"gasCost":3},{"pc":78,"gasCost":3},{"pc":79,"gasCost":3},{"pc":82,"gasCost":10},{"pc":83,"gasCost":3},{"pc":84,"gasCost":3},{"pc":89,"gasCost":3},{"pc":90,"gasCost":3},{"pc":93,"gasCost":10},{"pc":94,"gasCost":3},{"pc":95,"gasCost":3},{"pc":100,"gasCost":3},{"pc":101,"gasCost":3},{"pc":104,"gasCost":10},{"pc":105,"gasCost":3},{"pc":106,"gasCost":3},{"pc":111,"gasCost":3},{"pc":112,"gasCost":3},{"pc":115,"gasCost":10},{"pc":116,"gasCost":3},{"pc":117,"gasCost":3},{"pc":122,"gasCost":3},{"pc":123,"gasCost":3},{"pc":126,"gasCost":10},{"pc":544,"gasCost":1},{"pc":545,"gasCost":2},{"pc":546,"gasCost":3},{"pc":547,"gasCost":3},{"pc":550,"gasCost":10},{"pc":555,"gasCost":1},{"pc":556,"gasCost":3},{"pc":559,"gasCost":3},{"pc":561,"gasCost":3},{"pc":563,"gasCost":3},{"pc":565,"gasCost":60},{"pc":566,"gasCost":3},{"pc":567,"gasCost":3},{"pc":569,"gasCost":3},{"pc":570,"gasCost":3},{"pc":571,"gasCost":3},{"pc":573,"gasCost":3},{"pc":574,"gasCost":3},{"pc":577,"gasCost":8},{"pc":1487,"gasCost":1},{"pc":1488,"gasCost":3},{"pc":1490,"gasCost":3},{"pc":1492,"gasCost":3},{"pc":1494,"gasCost":60},{"pc":1495,"gasCost":3},{"pc":1496,"gasCost":2},{"pc":1497,"gasCost":3},{"pc":1498,"gasCost":3},{"pc":1500,"gasCost":3},{"pc":1501,"gasCost":3},{"pc":1502,"gasCost":3},{"pc":1503,"gasCost":3},{"pc":1505,"gasCost":3},{"pc":1507,"gasCost":3},{"pc":1508,"gasCost":3},{"pc":1510,"gasCost":3},{"pc":1511,"gasCost":42},{"pc":1512,"gasCost":200},{"pc":1513,"gasCost":3},{"pc":1514,"gasCost":3},{"pc":1515,"gasCost":3},{"pc":1516,"gasCost":3},{"pc":1517,"gasCost":3},{"pc":1518,"gasCost":3},{"pc":1519,"gasCost":3},{"pc":1522,"gasCost":10},{"pc":1523,"gasCost":2},{"pc":1524,"gasCost":3},{"pc":1526,"gasCost":3},{"pc":1527,"gasCost":3},{"pc":1528,"gasCost":1},{"pc":1529,"gasCost":3},{"pc":1530,"gasCost":3},{"pc":1533,"gasCost":10},{"pc":1534,"gasCost":3},{"pc":1536,"gasCost":3},{"pc":1538,"gasCost":3},{"pc":1540,"gasCost":60},{"pc":1541,"gasCost":3},{"pc":1542,"gasCost":2},{"pc":1543,"gasCost":3},{"pc":1544,"gasCost":3},{"pc":1545,"gasCost":3},{"pc":1547,"gasCost":3},{"pc":1548,"gasCost":3},{"pc":1549,"gasCost":3},{"pc":1550,"gasCost":3},{"pc":1552,"gasCost":3},{"pc":1554,"gasCost":3},{"pc":1555,"gasCost":3},{"pc":1557,"gasCost":3},{"pc":1558,"gasCost":3},{"pc":1559,"gasCost":42},{"pc":1560,"gasCost":3},{"pc":1561,"gasCost":200},{"pc":1562,"gasCost":3},{"pc":1563,"gasCost":3},{"pc":1564,"gasCost":3},{"pc":1565,"gasCost":3},{"pc":1566,"gasCost":5000},{"pc":1567,"gasCost":3},{"pc":1568,"gasCost":3},{"pc":1569,"gasCost":3},{"pc":1570,"gasCost":3},{"pc":1571,"gasCost":3},{"pc":1572,"gasCost":3},{"pc":1573,"gasCost":3},{"pc":1574,"gasCost":3},{"pc":1575,"gasCost":3},{"pc":1576,"gasCost":42},{"pc":1577,"gasCost":3},{"pc":1578,"gasCost":200},{"pc":1579,"gasCost":3},{"pc":1580,"gasCost":3},{"pc":1581,"gasCost":3},{"pc":1582,"gasCost":5000},{"pc":1583,"gasCost":3},{"pc":1584,"gasCost":3},{"pc":1617,"gasCost":3},{"pc":1618,"gasCost":3},{"pc":1619,"gasCost":3},{"pc":1620,"gasCost":3},{"pc":1621,"gasCost":3},{"pc":1622,"gasCost":3},{"pc":1623,"gasCost":6},{"pc":1624,"gasCost":3},{"pc":1626,"gasCost":3},{"pc":1627,"gasCost":3},{"pc":1629,"gasCost":3},{"pc":1630,"gasCost":3},{"pc":1631,"gasCost":3},{"pc":1632,"gasCost":3},{"pc":1633,"gasCost":3},{"pc":1634,"gasCost":1756},{"pc":1635,"gasCost":2},{"pc":1636,"gasCost":3},{"pc":1638,"gasCost":3},{"pc":1641,"gasCost":8},{"pc":977,"gasCost":1},{"pc":978,"gasCost":3},{"pc":979,"gasCost":3},{"pc":980,"gasCost":2},{"pc":981,"gasCost":2},{"pc":982,"gasCost":8},{"pc":337,"gasCost":1},{"pc":338,"gasCost":3},{"pc":340,"gasCost":3},{"pc":341,"gasCost":3},{"pc":342,"gasCost":3},{"pc":343,"gasCost":3},{"pc":344,"gasCost":3},{"pc":345,"gasCost":3},{"pc":346,"gasCost":3},{"pc":348,"gasCost":3},{"pc":349,"gasCost":3},{"pc":351,"gasCost":3},{"pc":352,"gasCost":3},{"pc":353,"gasCost":3},{"pc":354,"gasCost":3},{"pc":355,"gasCost":3},{"pc":356,"gasCost":0}]
